pyinfra_kubernetes/__init__.py
pyinfra_kubernetes/configure.py
pyinfra_kubernetes/defaults.py
pyinfra_kubernetes/install.py
pyinfra_kubernetes/util.py
pyinfra_kubernetes/templates/kube-apiserver.conf.j2
pyinfra_kubernetes/templates/kube-apiserver.service.j2
pyinfra_kubernetes/templates/kube-controller-manager.conf.j2
pyinfra_kubernetes/templates/kube-controller-manager.service.j2
pyinfra_kubernetes/templates/kube-proxy.conf.j2
pyinfra_kubernetes/templates/kube-proxy.service.j2
pyinfra_kubernetes/templates/kube-scheduler.conf.j2
pyinfra_kubernetes/templates/kube-scheduler.service.j2
pyinfra_kubernetes/templates/kubeconfig.yml.j2
pyinfra_kubernetes/templates/kubelet.conf.j2
pyinfra_kubernetes/templates/kubelet.service.j2
pyinfra_kubernetes-0.1.1.dist-info/DESCRIPTION.rst
pyinfra_kubernetes-0.1.1.dist-info/METADATA
pyinfra_kubernetes-0.1.1.dist-info/RECORD
pyinfra_kubernetes-0.1.1.dist-info/WHEEL
pyinfra_kubernetes-0.1.1.dist-info/metadata.json
pyinfra_kubernetes-0.1.1.dist-info/top_level.txt
