Metadata-Version: 2.0
Name: pyinfra-kubernetes
Version: 0.1.1
Summary: Install & bootstrap Kubernetes clusters with pyinfra.
Home-page: https://github.com/EDITD/pyinfra-kubernetes
Author: EDITED
Author-email: engineering@edited.com
License: MIT
Platform: UNKNOWN
Requires-Dist: pyinfra (>=0.5)
